{
  "hash": "0e536495bc4ea65418a8",
  "publicPath": "/",
  "outputPath": "/home/node/work/public",
  "assetsByChunkName": {
    "main": [
      "render-page.js"
    ]
  },
  "assets": [
    {
      "type": "assets by status",
      "cached": true,
      "filteredChildren": 1,
      "size": 5910748
    }
  ],
  "namedChunkGroups": {
    "main": {
      "name": "main",
      "chunks": [
        "main"
      ],
      "assets": [
        {
          "name": "render-page.js"
        }
      ],
      "filteredAssets": 0,
      "assetsSize": null,
      "filteredAuxiliaryAssets": 1,
      "auxiliaryAssetsSize": null,
      "children": {},
      "childAssets": {}
    }
  },
  "generator": "loadable-components",
  "chunks": [
    {
      "id": "main",
      "files": [
        "render-page.js"
      ]
    }
  ]
}